[
  {
    "title": "Ion",
    "client": {
      "name": "Pamela Swingle"
    },
    "startAt": "2025-01-31T05:00:00Z",
    "lineItems": {
      "edges": [
        {
          "node": {
            "description": "Location: Basement window 1 and 2 bottom \r\nGlass Type: Annealed low e soft \r\nSize:41 1/4 x 16 7/8 \r\nOA: 7/8 \r\nMuntin Bars: 1h 3v white 5/8 \r\n\r\nDisclaimer: Some Glass may require an additional visit for more precise measurements. \r\n\r\nPlease be advised:\r\nLead times may vary depending on the type of glass, ranging from 3 to 21 days.",
            "quantity": 2.0
          }
        },
        {
          "node": {
            "description": "Location: Basement window top \r\nGlass Type: Annealed low e soft\r\nSize:40 1/4 x 15 7/8 \r\nOA: 7/8 \r\nMuntin Bars: 1h 3v white 5/8 \r\n\r\nDisclaimer: Some Glass may require an additional visit for more precise measurements. \r\n\r\nPlease be advised:\r\nLead times may vary depending on the type of glass, ranging from 3 to 21 days.",
            "quantity": 1.0
          }
        },
        {
          "node": {
            "description": "Location: Bedroom 1, bottom \r\nGlass Type: Annealed low e soft \r\nSize:41 1/4 x 21 1/8 \r\nOA: 7/8 \r\nMuntin Bars: 1h 3v white 5/8 \r\n\r\nDisclaimer: Some Glass may require an additional visit for more precise measurements. \r\n\r\nPlease be advised:\r\nLead times may vary depending on the type of glass, ranging from 3 to 21 days.",
            "quantity": 1.0
          }
        }
      ]
    }
  },
  {
    "title": "Leo",
    "client": {
      "name": "Realty Executives Central"
    },
    "startAt": "2025-01-31T05:00:00Z",
    "lineItems": {
      "edges": [
        {
          "node": {
            "description": "Location: rear door SDL\r\nGlass Type: single tempered clear\r\nSize: 21 3/4 x 67\r\nOA: 1/8\r\nMuntin Bars: 0\r\n\r\nDisclaimer: Some Glass may require an additional visit for more precise measurements. \r\n\r\nPlease be advised:\r\nLead times may vary depending on the type of glass, ranging from 3 to 21 days.",
            "quantity": 1.0
          }
        }
      ]
    }
  }
]